AUTHORS
CHANGELOG
LICENSE
MANIFEST.in
README.rst
setup.py
amplecode/__init__.py
amplecode.recipe.template.egg-info/PKG-INFO
amplecode.recipe.template.egg-info/SOURCES.txt
amplecode.recipe.template.egg-info/dependency_links.txt
amplecode.recipe.template.egg-info/entry_points.txt
amplecode.recipe.template.egg-info/namespace_packages.txt
amplecode.recipe.template.egg-info/requires.txt
amplecode.recipe.template.egg-info/top_level.txt
amplecode.recipe.template.egg-info/zip-safe
amplecode/recipe/__init__.py
amplecode/recipe/template/__init__.py