Metadata-Version: 1.0
Name: amplecode.recipe.template
Version: 1.1
Summary: Buildout recipe for making files out of Jinja2 templates
Home-page: http://github.com/torgeilo/amplecode.recipe.template
Author: Torgeir Lorange Ostby
Author-email: torgeilo@gmail.com
License: BSD
Keywords: zc.buildout recipe template Jinja2
Platform: UNKNOWN
Classifier: Framework :: Buildout
Classifier: Intended Audience :: Developers
Classifier: License :: OSI Approved :: BSD License
Classifier: Programming Language :: Python
Classifier: Topic :: Software Development
Classifier: Topic :: Software Development :: Code Generators
Classifier: Topic :: Software Development :: Pre-processors
